{
    "options": [
        [
            {
                "item": "Peter: My name is Peter.",
                "answer": 2
            },
            {
                "item": "Peter : I’m a Doctor Nice to meet you, too.",
                "answer": 4
            },
            {
                "item": "Mary:  What´s your name?",
                "answer": 1
            },
            {
                "item": "Mary: Nice to meet you. What´s your job?",
                "answer": 3
            }
        ],
        [
            {
                "item": "Peter: My name is Peter.",
                "answer": 2
            },
            {
                "item": "Peter : I’m a Doctor Nice to meet you, too.",
                "answer": 4
            },
            {
                "item": "Mary:  What´s your name?",
                "answer": 1
            },
            {
                "item": "Mary: Nice to meet you. What´s your job?",
                "answer": 3
            }
        ],
        [
            {
                "item": "Peter: My name is Peter.",
                "answer": 2
            },
            {
                "item": "Peter : I’m a Doctor Nice to meet you, too.",
                "answer": 4
            },
            {
                "item": "Mary:  What´s your name?",
                "answer": 1
            },
            {
                "item": "Mary: Nice to meet you. What´s your job?",
                "answer": 3
            }
        ],
        [
            {
                "item": "Peter: My name is Peter.",
                "answer": 2
            },
            {
                "item": "Peter : I’m a Doctor Nice to meet you, too.",
                "answer": 4
            },
            {
                "item": "Mary:  What´s your name?",
                "answer": 1
            },
            {
                "item": "Mary: Nice to meet you. What´s your job?",
                "answer": 3
            }
        ],
        [
            {
                "item": "Peter: My name is Peter.",
                "answer": 2
            },
            {
                "item": "Peter : I’m a Doctor Nice to meet you, too.",
                "answer": 4
            },
            {
                "item": "Mary:  What´s your name?",
                "answer": 1
            },
            {
                "item": "Mary: Nice to meet you. What´s your job?",
                "answer": 3
            }
        ],
        [
            {
                "item": "Peter: My name is Peter.",
                "answer": 2
            },
            {
                "item": "Peter : I’m a Doctor Nice to meet you, too.",
                "answer": 4
            },
            {
                "item": "Mary:  What´s your name?",
                "answer": 1
            },
            {
                "item": "Mary: Nice to meet you. What´s your job?",
                "answer": 3
            }
        ],
        [
            {
                "item": "Peter: My name is Peter.",
                "answer": 2
            },
            {
                "item": "Peter : I’m a Doctor Nice to meet you, too.",
                "answer": 4
            },
            {
                "item": "Mary:  What´s your name?",
                "answer": 1
            },
            {
                "item": "Mary: Nice to meet you. What´s your job?",
                "answer": 3
            }
        ],
        [
            {
                "item": "Peter: My name is Peter.",
                "answer": 2
            },
            {
                "item": "Peter : I’m a Doctor Nice to meet you, too.",
                "answer": 4
            },
            {
                "item": "Mary:  What´s your name?",
                "answer": 1
            },
            {
                "item": "Mary: Nice to meet you. What´s your job?",
                "answer": 3
            }
        ]                                                       
    ],
    "body": [],
    "_id": "6133aa1062a77824887c0f77",
    "task_id": "6133a93562a77824887c0f6b",
    "type": "ordenar",
    "question": "Order the next dialogue",
    "__v": 0
}
